[
  {
    "utterance_id": "u001",
    "start": 0.0,
    "end": 0.74,
    "duration": 0.74,
    "transcript": "랩 랩다!",
    "word_count": 2,
    "words": [
      {
        "text": "랩",
        "start": 0.0,
        "end": 0.4,
        "confidence": 0.5134
      },
      {
        "text": "랩다!",
        "start": 0.4,
        "end": 0.74,
        "confidence": 0.8368
      }
    ],
    "vad_segment_start": 0.0,
    "vad_segment_end": 0.75,
    "features": {
      "speech_rate_wpm": null,
      "speech_rate_wps": null,
      "articulation_rate": null,
      "pause_count": null,
      "pause_rate": null,
      "mean_pause_duration": null,
      "std_pause_duration": null,
      "total_pause_time": null,
      "speaking_time_ratio": null,
      "pitch_mean": null,
      "pitch_std": null,
      "pitch_range": null,
      "pitch_variance": null,
      "voiced_frames_ratio": null,
      "rms_energy_mean": null,
      "rms_energy_std": null,
      "rms_energy_max": null,
      "rms_energy_min": null,
      "energy_dynamic_range": null,
      "zero_crossing_rate": null,
      "harmonic_noise_ratio": null,
      "spectral_centroid_mean": null,
      "spectral_centroid_std": null,
      "mfcc_1_mean": null,
      "mfcc_2_mean": null,
      "mfcc_1_std": null,
      "spectral_rolloff": null,
      "spectral_bandwidth": null,
      "snr_approximation": null,
      "clipping_ratio": null
    },
    "asr_confidence": 0.675,
    "speech_rate_wps": 2.703,
    "speech_rate_wpm": 162.162,
    "articulation_rate": 2.703,
    "pause_count": 0,
    "pause_rate": 0.0,
    "mean_pause_duration": 0.0,
    "std_pause_duration": 0.0,
    "total_pause_time": 0.0,
    "speaking_time_ratio": 1.0,
    "pitch_mean": 309.815,
    "pitch_std": 44.342,
    "pitch_range": 141.774,
    "pitch_variance": 1966.252,
    "voiced_frames_ratio": 0.833,
    "rms_energy_mean": 0.083,
    "rms_energy_std": 0.05,
    "rms_energy_max": 0.168,
    "rms_energy_min": 0.017,
    "energy_dynamic_range": 0.15,
    "zero_crossing_rate": 0.101,
    "harmonic_noise_ratio": 0.906,
    "spectral_centroid_mean": 1553.455,
    "spectral_centroid_std": 266.152,
    "mfcc_1_mean": -183.354,
    "mfcc_2_mean": 98.937,
    "mfcc_1_std": 66.445,
    "spectral_rolloff": 3038.086,
    "spectral_bandwidth": 1494.818,
    "snr_approximation": 1.672,
    "clipping_ratio": 0.0
  }
]