[
  {
    "utterance_id": "u001",
    "start": 0.0,
    "end": 0.7,
    "duration": 0.7,
    "transcript": "El ojelo",
    "word_count": 2,
    "words": [
      {
        "text": "el",
        "start": 0.0,
        "end": 0.28,
        "confidence": 0.3362
      },
      {
        "text": "ojelo",
        "start": 0.28,
        "end": 0.7,
        "confidence": 0.4741
      }
    ],
    "vad_segment_start": 0.0,
    "vad_segment_end": 1.05,
    "features": {
      "speech_rate_wpm": null,
      "speech_rate_wps": null,
      "articulation_rate": null,
      "pause_count": null,
      "pause_rate": null,
      "mean_pause_duration": null,
      "std_pause_duration": null,
      "total_pause_time": null,
      "speaking_time_ratio": null,
      "pitch_mean": null,
      "pitch_std": null,
      "pitch_range": null,
      "pitch_variance": null,
      "voiced_frames_ratio": null,
      "rms_energy_mean": null,
      "rms_energy_std": null,
      "rms_energy_max": null,
      "rms_energy_min": null,
      "energy_dynamic_range": null,
      "zero_crossing_rate": null,
      "harmonic_noise_ratio": null,
      "spectral_centroid_mean": null,
      "spectral_centroid_std": null,
      "mfcc_1_mean": null,
      "mfcc_2_mean": null,
      "mfcc_1_std": null,
      "spectral_rolloff": null,
      "spectral_bandwidth": null,
      "snr_approximation": null,
      "clipping_ratio": null
    },
    "asr_confidence": 0.405,
    "speech_rate_wps": 2.857,
    "speech_rate_wpm": 171.429,
    "articulation_rate": 2.857,
    "pause_count": 0,
    "pause_rate": 0.0,
    "mean_pause_duration": 0.0,
    "std_pause_duration": 0.0,
    "total_pause_time": 0.0,
    "speaking_time_ratio": 1.0,
    "pitch_mean": 258.101,
    "pitch_std": 13.643,
    "pitch_range": 43.876,
    "pitch_variance": 186.123,
    "voiced_frames_ratio": 1.0,
    "rms_energy_mean": 0.082,
    "rms_energy_std": 0.037,
    "rms_energy_max": 0.126,
    "rms_energy_min": 0.012,
    "energy_dynamic_range": 0.113,
    "zero_crossing_rate": 0.152,
    "harmonic_noise_ratio": 2.32,
    "spectral_centroid_mean": 2033.17,
    "spectral_centroid_std": 375.028,
    "mfcc_1_mean": -162.23,
    "mfcc_2_mean": 72.311,
    "mfcc_1_std": 75.216,
    "spectral_rolloff": 3955.256,
    "spectral_bandwidth": 1608.425,
    "snr_approximation": 2.226,
    "clipping_ratio": 0.0
  }
]