[
  {
    "type": "no_face_detected",
    "timestamp": "2025-11-18T07:22:22.091Z",
    "details": {
      "raw": "detector returned 0 faces",
      "question": "What is cross-validation, and why is it used?"
    }
  },
  {
    "type": "tab_switch",
    "timestamp": "2025-11-18T07:22:49.430Z",
    "details": {
      "raw": "Window focus lost (switched to another application)",
      "question": "What is cross-validation, and why is it used?"
    }
  },
  {
    "type": "tab_switch",
    "timestamp": "2025-11-18T07:22:49.693Z",
    "details": {
      "raw": "Tab switched or minimized",
      "question": "What is cross-validation, and why is it used?"
    }
  }
]